[
    {
      "category_id": "637f2b9aef46343e5857af67",
      "img":"https://images.unsplash.com/photo-1591337676887-a217a6970a8a?ixlib=rb-4.0.3&ixid=MnwxMjA3fDB8MHxzZWFyY2h8MXx8aXBob25lJTIwMTF8ZW58MHx8MHx8&w=1000&q=80",
      "model":"iphone 11",
      "resalePrice": "50,000",
      "orginalPrice":"99,999",
      "location":"Rajshahi",
      "usedYear":"1 year",
      "postTime":"24 November, 2022",
      "sellerName":"Arfin Taif",
      "condition":"Good",
      "mobileNumber":"01738-458795",
      "purchasesYear":"2022",
      "description":"Apple iPhone 11 comes with 6.1 inches Liquid Retina IPS LCD screen. It has a classical Apple iPhone notch design. The back camera is of Dual 12+12 MP with powerful image processing capability and Ultra HD 4K video recording. The front camera is of Dual 12 MP and SL 3D camera. Apple iPhone 11 comes with 3110 mAh battery with 18W fast charging solution. It has 4 GB RAM, up to 2.65 GHz hexa-core CPU and Apple GPU. It is powered by Apple A13 Bionic (7 nm+) chipset. The device comes with 64, 128 or 256 GB internal storage. There is no fingerprint sensor in this device."
    },
    {
      "category_id": "637f2b9aef46343e5857af67",
      "img":"https://www.91-img.com/gallery_images_uploads/4/8/48bf66badf23152537ad6006502eb507d4aefbde.JPG?tr=h-550,w-0,c-at_max",
      "model":"iphone 12 Pro Max",
      "resalePrice": "92,000",
      "orginalPrice":"124,999",
      "location":"Dhaka",
      "usedYear":"6 month",
      "postTime":"17 November, 2022",
      "sellerName":"Shariar Istiak",
      "condition":"Excellent",
      "mobileNumber":"01945-892351",
      "purchasesYear":"2022",
      "description":"Apple iPhone 12 Pro Max comes with a 6.1 inches Super Retina XDR OLED screen which is one of its main specialties. It has a classical Apple iPhone notch design. The back camera is of dual 12+12 MP with powerful image processing capability and 4K video recording. The front one is of Dual 12 MP and SL 3D camera. Apple iPhone 12 comes with Li-ion battery with 18W fast charging solution. It has 6 GB RAM, Hexa-core CPU and Apple GPU. It is powered by a 5 nm Apple A14 Bionic chipset. The device comes with 64, 128 or 256 GB internal storage."
    },
    
    {
      "category_id": "637f2b9aef46343e5857af68",
      "img":"https://www.91-img.com/gallery_images_uploads/a/9/a9ee746a5598c2e4c8ea5730df0342e124f650a8.jpg?tr=h-550,w-0,c-at_max",
      "model":"Realme 8",
      "resalePrice": "20,000",
      "orginalPrice":"27,000",
      "location":"Rajshahi",
      "usedYear":"1 year",
      "postTime":"20 November, 2022",
      "sellerName":"Nafis Fahim",
      "condition":"Excellent",
      "mobileNumber":"01521-3348985",
      "purchasesYear":"2021",
      "description":"Realme 8 comes with 6.4 inches Full HD+ Super AMOLED screen. It has a Full-View left punch-hole design. The back camera is of quad 64+8+2+2 MP with PDAF, dedicated macro camera, depth sensor, ultrawide lens etc. and 4K video recording. The front camera is of 16 MP. Realme 8 comes with 5000 mAh battery with 30W Fast Charging. It has 8 GB RAM, up to 2.05 GHz octa-core CPU and Mali-G76 MC4 GPU. It is powered by a Mediatek Helio G95 (12 nm) chipset. The device comes with 128 GB internal storage and dedicated MicroSD slot. There is a in-display fingerprint sensor in this phone."
    },
    {
      "category_id": "637f2b9aef46343e5857af68",
      "img":"https://root-nation.com/wp-content/uploads/2021/08/vivo-V21-1-696x392.jpg",
      "model":"Vivo V21",
      "resalePrice": "22,000",
      "orginalPrice":"33,000",
      "location":"Khulna",
      "usedYear":"1 year",
      "postTime":"10 November, 2022",
      "sellerName":"Tanvir Islam",
      "condition":"Good",
      "mobileNumber":"01858-487563",
      "purchasesYear":"2022",
      "description":"Vivo V21 comes with 6.44 inches Full HD+ AMOLED screen. It has a waterdrop notch front camera design. The back camera is of triple 64+8+2 MP with PDAF, ultrawide, OIS, macro lens, LED flash etc. and 4K video recording. The front camera is of 44 MP. Vivo V21 comes with 4000 mAh battery with 33W Fast Charging. It has 8 GB RAM, up to 2.4 GHz octa-core CPU and Mali-G57 MC3 GPU. It is powered by a MediaTek Dimensity 800U 5G (7 nm) chipset. The device comes with 128 GB internal storage and shared MicroSD slot. There is an in-display (optical) fingerprint sensor in this phone."
    },
    
    {
      "category_id": "637f2b9aef46343e5857af69",
      "img":"https://www.gizbot.com/images/2019-09/nokia-110-2019_156785107290.jpg",
      "model":"Nokia 110",
      "resalePrice": "2000",
      "orginalPrice":"4000",
      "location":"Chittagong",
      "usedYear":"5 month",
      "postTime":"01 November, 2022",
      "sellerName":"Fabiha Buhsra",
      "condition":"Excellent",
      "mobileNumber":"01987-486985",
      "purchasesYear":"2022",
      "description":"The price of the Nokia 110 (2019) is BDT 2,399. Nokia 110 (2019) feature phone comes to some extra games and it has 1.77 inches, 9.7 cm2 (~16.9% screen-to-body ratio), TFT, 66K colors and resolution is 120 x 160 pixels, 4:3 ratio (~113 ppi density). It has 4 MB internal storage, which can expand up to 32 GB (dedicated slot) external storage. This stylish device has a QVGA front camera. It was powered by a standard 800 mAh Removal Li-Ion battery."
    },
    {
      "category_id": "637f2b9aef46343e5857af69",
      "img":"https://akm-img-a-in.tosshub.com/indiatoday/images/story/201502/nokia-650-x-418_022015110051.jpg?VersionId=AP1BjivYd.Wv3C6_qve9vH4Kb5svkt8j&size=690:388",
      "model":"Nokia 215",
      "resalePrice": "5000",
      "orginalPrice":"3500",
      "location":"Khulna",
      "usedYear":"1 year",
      "postTime":"11 November, 2022",
      "sellerName":"Faiza Ishra",
      "condition":"Good",
      "mobileNumber":"013-879651",
      "purchasesYear":"2022",
      "description":"The price of the Nokia 215 4G is BDT 4,500. 215 4G featured phone comes with 2.4 inches, 17.8 cm2 (~28.0% screen-to-body ratio), TFT, 256K colors display, and a resolution of 240 x 320 pixels, 4:3 ratio (~167 ppi density). ) chipset. The phone has an internal memory of 128 MB, which can keep a lot of files and data of the user. This stylish device has a No camera in the back and no camera on the front side. It was powered by a standard 1150 mAh Li-ion battery."
    }
]